[
       {
          "Question": "What are some random fun facts about you?",
          "Id": "1661023801"
        },
        {
          "Question": "What's your favorite place on Earth?",
          "Id": "1661023802"
        },
        {
          "Question": "Who are the special people in your life?",
          "Id": "1661023803"
        },
        {
          "Question": "What's something you're proud of?",
          "Id": "1661023804"
        },
        {
          "Question": "What's something that makes you unique?",
          "Id": "1661023805"
        }
]
